{
  "elements": [
    {
      "id": "mariner.halfheart",
      "label": "My Half-Heart",
      "description": "My passions, my drive, my charm, my thrumming blood, my clever fingers. If I present this to the world, I may be able to bend things to my will. [Use this while Exploring, Talking or Performing, and you may find or discuss things of interest to you]"
    },
    {
      "id": "mariner.halfheart.exhausted",
      "label": "My Half-Heart [exhausted]",
      "description": "My passions, my drive, my charm, my thrumming blood, my clever fingers. Each need a rest."
    },
    {
      "id": "mariner.lackheart",
      "label": "My Lack-Heart",
      "description": "A wound in the soul, a raw nerve, a longing. If I leave this exposed, the universe will try to fill it. [Use this while Exploring, Talking or Performing and you may find Tunes, Stories or other Inspirations]"
    },
    {
      "id": "mariner.lackheart.exhausted",
      "label": "My Lack-Heart [exhausted]",
      "description": "A wound in the soul, a raw nerve, a longing. I could not bear to expose it now."
    }
  ]
}